garjus/__init__.py
garjus/cli.py
garjus/dictionary.py
garjus/garjus.py
garjus/import_dicom.py
garjus/utils_dcm2nii.py
garjus/utils_redcap.py
garjus/utils_xnat.py
garjus/analyses/__init__.py
garjus/automations/ACOBA_crt.py
garjus/automations/ACOBA_nback.py
garjus/automations/ACOBA_posner.py
garjus/automations/__init__.py
garjus/automations/all_stats_FS7.py
garjus/automations/all_stats_msit.py
garjus/automations/edat_convert2tab.py
garjus/automations/edat_limbo2redcap.py
garjus/automations/edat_redcap2xnat.py
garjus/automations/etl_fallypride.py
garjus/automations/lifedata_box2redcap.py
garjus/automations/lifedata_file2redcap.py
garjus/automations/more_stats_FS7.py
garjus/automations/plasmacrp.py
garjus/automations/xnat_add_slicetiming.py
garjus/automations/xnat_auto_archive.py
garjus/automations/xnat_dcm2niix.py
garjus/automations/xnat_ma3stats2voltxt.py
garjus/automations/xnat_relabel_scans.py
garjus/automations/xnat_relabel_sessions.py
garjus/automations/etl_arcapp/__init__.py
garjus/automations/etl_arcapp/dailyweekly.py
garjus/automations/etl_arcapp/extract_context_xml.py
garjus/automations/etl_arcdata/__init__.py
garjus/automations/etl_arcdata/file2redcap.py
garjus/automations/etl_arcdata/summary.py
garjus/automations/etl_fitbit/__init__.py
garjus/automations/etl_fitbit/file2redcap.py
garjus/automations/etl_gaitrite/__init__.py
garjus/automations/etl_lifedata/__init__.py
garjus/automations/etl_lifedata/dailyweekly.py
garjus/automations/etl_nihexaminer/__init__.py
garjus/automations/etl_nihexaminer/file2redcap.py
garjus/automations/etl_nihexaminer/process.py
garjus/automations/etl_nihexaminer/run_manual_7500wk12.py
garjus/automations/etl_nihexaminer/run_manual_7577wk12.py
garjus/automations/etl_nihtoolbox_drnair/__init__.py
garjus/automations/etl_nihtoolbox_drnair/split_files.py
garjus/automations/etl_nihtoolbox_drtaylor/__init__.py
garjus/automations/etl_traitadjrecall/__init__.py
garjus/automations/etl_traitadjtask/__init__.py
garjus/compare/__init__.py
garjus-1.3.8.dist-info/LICENSE
garjus-1.3.8.dist-info/METADATA
garjus-1.3.8.dist-info/WHEEL
garjus-1.3.8.dist-info/entry_points.txt
garjus-1.3.8.dist-info/top_level.txt
garjus-1.3.8.dist-info/RECORD
