Metadata-Version: 2.1
Name: garjus
Version: 1.3.8
Summary: Python package for managing imaging research projects in REDCap and XNAT
Home-page: https://github.com/ccmvumc/garjus
Author: Brian D. Boyd
Author-email: brian.d.boyd@vumc.org
Classifier: Development Status :: 4 - Beta
Classifier: License :: OSI Approved :: MIT License
Classifier: Programming Language :: Python :: 3
Classifier: Programming Language :: Python :: 3.10
License-File: LICENSE
Requires-Dist: pandas
Requires-Dist: pycap
Requires-Dist: pyxnat
Requires-Dist: dax
Requires-Dist: click
Requires-Dist: sphinx
Requires-Dist: pydot
Requires-Dist: plotly
Requires-Dist: dash_bootstrap_components
Requires-Dist: dash_bootstrap_templates
Requires-Dist: dash<3.0.0
Requires-Dist: flask_login
